LICENSE
README.md
setup.py
obd/OBDCommand.py
obd/OBDResponse.py
obd/UnitsAndScaling.py
obd/__init__.py
obd/__version__.py
obd/asynchronous.py
obd/codes.py
obd/commands.py
obd/decoders.py
obd/elm327.py
obd/obd.py
obd/utils.py
obd.egg-info/PKG-INFO
obd.egg-info/SOURCES.txt
obd.egg-info/dependency_links.txt
obd.egg-info/not-zip-safe
obd.egg-info/requires.txt
obd.egg-info/top_level.txt
obd/protocols/__init__.py
obd/protocols/protocol.py
obd/protocols/protocol_can.py
obd/protocols/protocol_legacy.py
obd/protocols/protocol_unknown.py