Metadata-Version: 2.1
Name: obd
Version: 0.7.2
Summary: Serial module for handling live sensor data from a vehicle's OBD-II port
Home-page: http://github.com/brendan-w/python-OBD
Author: Brendan Whitfield
Author-email: brendanw@windworksdesign.com
License: GNU GPLv2
Keywords: obd obdii obd-ii obd2 car serial vehicle diagnostic
Classifier: Operating System :: POSIX :: Linux
Classifier: License :: OSI Approved :: GNU General Public License v2 (GPLv2)
Classifier: Topic :: System :: Monitoring
Classifier: Programming Language :: Python :: 2
Classifier: Programming Language :: Python :: 3
Classifier: Development Status :: 3 - Alpha
Classifier: Topic :: System :: Logging
Classifier: Intended Audience :: Developers
License-File: LICENSE
